mast_aladin/__init__.py
mast_aladin/aida.py
mast_aladin/app.py
mast_aladin/app_sidecar.py
mast_aladin/conftest.py
mast_aladin/mixins.py
mast_aladin/adapters/__init__.py
mast_aladin/adapters/aladin_sync_adapter.py
mast_aladin/adapters/imviz_sync_adapter.py
mast_aladin/adapters/sync_manager.py
mast_aladin/adapters/viewer_sync_adapter.py
mast_aladin/adapters/viewer_sync_ui.py
mast_aladin/overlay/mast_overlay.py
mast_aladin/overlay/overlay_manager.py
mast_aladin/table/__init__.py
mast_aladin/table/mast_table.py
mast_aladin/table/mast_table.vue
mast_aladin/table/validate.py
mast_aladin/table/data/column_descriptions.json
mast_aladin/table/data/unique_columns_per_mission.json
mast_aladin/tests/__init__.py
mast_aladin/tests/test_aida_example.py
mast_aladin/tests/test_app.py
mast_aladin/tests/test_example.py
mast_aladin/tests/test_mast_table.py
mast_aladin/tests/test_overlays_dict.py
mast_aladin/tests/test_overlays_update.py
mast_aladin/tests/test_utils.py
mast_aladin/tests/adapters/__init__.py
mast_aladin/tests/adapters/test_sync_adapters.py
mast_aladin/tests/data/mm_jwst_M4.ecsv
mast_aladin-0.0.2.dist-info/licenses/LICENSE
mast_aladin-0.0.2.dist-info/METADATA
mast_aladin-0.0.2.dist-info/WHEEL
mast_aladin-0.0.2.dist-info/top_level.txt
mast_aladin-0.0.2.dist-info/RECORD
