Metadata-Version: 2.4
Name: mast-aladin
Version: 0.0.2
Summary: Visualize MAST data products in Aladin Lite
Author-email: mast-aladin developers <help@stsci.edu>
License: BSD 3-Clause License
Project-URL: Homepage, https://mast-aladin.readthedocs.io/en/latest/
Requires-Python: >=3.11
License-File: LICENSE
Requires-Dist: astroquery
Requires-Dist: sidecar
Requires-Dist: jdaviz
Requires-Dist: traitlets
Requires-Dist: ipypopout
Requires-Dist: ipyvuetify
Requires-Dist: ipywidgets
Requires-Dist: solara
Provides-Extra: test
Requires-Dist: pytest; extra == "test"
Provides-Extra: docs
Requires-Dist: sphinx-astropy[confv2]>=1.9.1; extra == "docs"
Requires-Dist: sphinx_design; extra == "docs"
Dynamic: license-file
